README.md
pyproject.toml
setup.cfg
setup.py
src/mentat_misp_connector/__init__.py
src/mentat_misp_connector/component_misper.py
src/mentat_misp_connector/module_misper.py
src/mentat_misp_connector.egg-info/PKG-INFO
src/mentat_misp_connector.egg-info/SOURCES.txt
src/mentat_misp_connector.egg-info/dependency_links.txt
src/mentat_misp_connector.egg-info/requires.txt
src/mentat_misp_connector.egg-info/top_level.txt