Metadata-Version: 1.2
Name: mentat-misp-connector
Version: 0.1.1
Summary: Basic proprietary module used for integration of MISP platform into Cesnet's Mentat system.
Home-page: https://github.com/Aisik00/mentat-misp-connector
Author: Pavel Eis
Author-email: eis@cesnet.cz
License: MIT
Download-URL: https://github.com/Aisik00/mentat-misp-connector/archive/refs/tags/v0.1.1-alpha.tar.gz
Keywords: Mentat,MISP,integration
Platform: UNKNOWN
Classifier: Development Status :: 3 - Alpha
Classifier: Intended Audience :: Developers
Classifier: Topic :: Software Development :: Build Tools
Classifier: License :: OSI Approved :: MIT License
Classifier: Programming Language :: Python :: 3.6
Classifier: Programming Language :: Python :: 3.8
Requires-Python: >=3.6
